{
  "channel": "a+",
  "date": "15/02/2026",
  "schedule": [
    {
      "show_name": "La venganza de Gabino Barrera",
      "show_logo": "",
      "show_category": "",
      "start_time": "00:00",
      "end_time": "00:00",
      "episode_description": ""
    },
    {
      "show_name": "Infomerciales",
      "show_logo": "",
      "show_category": "",
      "start_time": "00:00",
      "end_time": "00:30",
      "episode_description": ""
    },
    {
      "show_name": "Sognare",
      "show_logo": "",
      "show_category": "",
      "start_time": "00:30",
      "end_time": "01:00",
      "episode_description": ""
    },
    {
      "show_name": "Infomerciales",
      "show_logo": "",
      "show_category": "",
      "start_time": "01:00",
      "end_time": "01:30",
      "episode_description": ""
    },
    {
      "show_name": "Sognare",
      "show_logo": "",
      "show_category": "",
      "start_time": "01:30",
      "end_time": "02:00",
      "episode_description": ""
    },
    {
      "show_name": "Infomerciales",
      "show_logo": "",
      "show_category": "",
      "start_time": "02:00",
      "end_time": "02:30",
      "episode_description": ""
    },
    {
      "show_name": "Sognare",
      "show_logo": "",
      "show_category": "",
      "start_time": "02:30",
      "end_time": "03:00",
      "episode_description": ""
    },
    {
      "show_name": "Infomerciales",
      "show_logo": "",
      "show_category": "",
      "start_time": "03:00",
      "end_time": "04:00",
      "episode_description": ""
    },
    {
      "show_name": "Sognare",
      "show_logo": "",
      "show_category": "",
      "start_time": "04:00",
      "end_time": "04:30",
      "episode_description": ""
    },
    {
      "show_name": "Infomerciales",
      "show_logo": "",
      "show_category": "",
      "start_time": "04:30",
      "end_time": "08:30",
      "episode_description": ""
    },
    {
      "show_name": "Sognare",
      "show_logo": "",
      "show_category": "",
      "start_time": "08:30",
      "end_time": "09:00",
      "episode_description": ""
    },
    {
      "show_name": "Naturista Naturalmente",
      "show_logo": "",
      "show_category": "",
      "start_time": "09:00",
      "end_time": "10:00",
      "episode_description": ""
    },
    {
      "show_name": "Infomerciales",
      "show_logo": "",
      "show_category": "",
      "start_time": "10:00",
      "end_time": "14:00",
      "episode_description": ""
    },
    {
      "show_name": "Pistoleros del oeste",
      "show_logo": "",
      "show_category": "",
      "start_time": "14:00",
      "end_time": "15:30",
      "episode_description": ""
    },
    {
      "show_name": "Quietos Todos",
      "show_logo": "",
      "show_category": "",
      "start_time": "15:30",
      "end_time": "17:00",
      "episode_description": ""
    },
    {
      "show_name": "Pancho Pistolas IV",
      "show_logo": "",
      "show_category": "",
      "start_time": "17:00",
      "end_time": "18:45",
      "episode_description": ""
    },
    {
      "show_name": "Narcotráfico Sentencia",
      "show_logo": "",
      "show_category": "",
      "start_time": "18:45",
      "end_time": "20:30",
      "episode_description": ""
    },
    {
      "show_name": "Traficante por Ambición",
      "show_logo": "",
      "show_category": "",
      "start_time": "20:30",
      "end_time": "22:15",
      "episode_description": ""
    },
    {
      "show_name": "El navegante",
      "show_logo": "",
      "show_category": "",
      "start_time": "22:15",
      "end_time": "00:00",
      "episode_description": ""
    }
  ]
}