{
  "channel": "Adrenalina Sports Network",
  "date": "12/03/2026",
  "schedule": [
    {
      "show_name": "El Inframundo",
      "show_logo": "",
      "show_category": "",
      "start_time": "00:00",
      "end_time": "00:00",
      "episode_description": ""
    },
    {
      "show_name": "El Inframundo",
      "show_logo": "",
      "show_category": "",
      "start_time": "00:00",
      "end_time": "01:00",
      "episode_description": ""
    },
    {
      "show_name": "Reto 4 Elementos",
      "show_logo": "",
      "show_category": "",
      "start_time": "01:00",
      "end_time": "02:45",
      "episode_description": ""
    },
    {
      "show_name": "La guarida del Mostro",
      "show_logo": "",
      "show_category": "",
      "start_time": "02:45",
      "end_time": "03:40",
      "episode_description": ""
    },
    {
      "show_name": "Corrida de Toros",
      "show_logo": "",
      "show_category": "",
      "start_time": "03:40",
      "end_time": "06:25",
      "episode_description": ""
    },
    {
      "show_name": "Lopes vs. Mandarina\nRepetición",
      "show_logo": "",
      "show_category": "",
      "start_time": "06:25",
      "end_time": "07:45",
      "episode_description": ""
    },
    {
      "show_name": "El Inframundo",
      "show_logo": "",
      "show_category": "",
      "start_time": "07:45",
      "end_time": "09:30",
      "episode_description": ""
    },
    {
      "show_name": "Reto 4 Elementos",
      "show_logo": "",
      "show_category": "",
      "start_time": "09:30",
      "end_time": "11:15",
      "episode_description": ""
    },
    {
      "show_name": "La guarida del Mostro",
      "show_logo": "",
      "show_category": "",
      "start_time": "11:15",
      "end_time": "12:10",
      "episode_description": ""
    },
    {
      "show_name": "Corrida de Toros",
      "show_logo": "",
      "show_category": "",
      "start_time": "12:10",
      "end_time": "15:00",
      "episode_description": ""
    },
    {
      "show_name": "Drako vs. Hooligan 2\nRepetición",
      "show_logo": "",
      "show_category": "",
      "start_time": "15:00",
      "end_time": "16:00",
      "episode_description": ""
    },
    {
      "show_name": "El Inframundo",
      "show_logo": "",
      "show_category": "",
      "start_time": "16:00",
      "end_time": "17:35",
      "episode_description": ""
    },
    {
      "show_name": "Reto 4 Elementos",
      "show_logo": "",
      "show_category": "",
      "start_time": "17:35",
      "end_time": "19:20",
      "episode_description": ""
    },
    {
      "show_name": "La guarida del Mostro",
      "show_logo": "",
      "show_category": "",
      "start_time": "19:20",
      "end_time": "20:15",
      "episode_description": ""
    },
    {
      "show_name": "Corrida de Toros",
      "show_logo": "",
      "show_category": "",
      "start_time": "20:15",
      "end_time": "23:05",
      "episode_description": ""
    },
    {
      "show_name": "El Inframundo",
      "show_logo": "",
      "show_category": "",
      "start_time": "23:05",
      "end_time": "00:00",
      "episode_description": ""
    }
  ]
}