{
  "channel_name": "Canal Sony (México)",
  "date": "2026-02-01",
  "programs": [
    {
      "show_name": "Corazones de Hierro (Fury)",
      "show_logo": "https://imagenes.gatotv.com/categorias/peliculas/miniatura/corazones_de_hierro_fury.jpg",
      "start_time": "2026-02-01 00:00:00",
      "end_time": "2026-02-01 01:30:00",
      "episode_number": "",
      "show_category": "Acción",
      "show_description": "En Abril de 1945, cuando los aliados hacen su enfrentamiento final en el campo europeo, un sargento de combate llamado Wardaddy (Brad Pitt) envía un tanque Sherman con su equipo de cinco hombres en una misión altamente peligrosa detrás de las líneas enemigas. A pesar de ser superados en número y armamento, Wardaddy y sus hombres intentarán atacar el corazón de la Alemania Nazi."
    },
    {
      "show_name": "Casados con Hijos",
      "show_logo": "",
      "start_time": "2026-02-01 01:30:00",
      "end_time": "2026-02-01 02:00:00",
      "episode_number": "S2 E12",
      "show_category": "",
      "show_description": ""
    },
    {
      "show_name": "The Good Doctor",
      "show_logo": "https://imagenes.gatotv.com/categorias/programas/miniatura/the_good_doctor.jpg",
      "start_time": "2026-02-01 02:00:00",
      "end_time": "2026-02-01 03:00:00",
      "episode_number": "S1 E13",
      "show_category": "Drama",
      "show_description": "Shaun Murphy (Freddie Highmore) es un joven cirujano con autismo y síndrome de erudito, se traslada de una vida tranquila en el campo para unirse a la prestigiosa unidad quirúrgica de un hospital. Solo en el mundo y sin poder conectarse personalmente con quienes lo rodean, Shaun utiliza sus extraordinarios dones médicos para salvar vidas y desafiar el escepticismo de sus colegas."
    },
    {
      "show_name": "The Good Doctor",
      "show_logo": "https://imagenes.gatotv.com/categorias/programas/miniatura/the_good_doctor.jpg",
      "start_time": "2026-02-01 03:00:00",
      "end_time": "2026-02-01 04:00:00",
      "episode_number": "S1 E14",
      "show_category": "Drama",
      "show_description": "Shaun Murphy (Freddie Highmore) es un joven cirujano con autismo y síndrome de erudito, se traslada de una vida tranquila en el campo para unirse a la prestigiosa unidad quirúrgica de un hospital. Solo en el mundo y sin poder conectarse personalmente con quienes lo rodean, Shaun utiliza sus extraordinarios dones médicos para salvar vidas y desafiar el escepticismo de sus colegas."
    },
    {
      "show_name": "The Good Doctor",
      "show_logo": "https://imagenes.gatotv.com/categorias/programas/miniatura/the_good_doctor.jpg",
      "start_time": "2026-02-01 04:00:00",
      "end_time": "2026-02-01 05:00:00",
      "episode_number": "S1 E15",
      "show_category": "Drama",
      "show_description": "Shaun Murphy (Freddie Highmore) es un joven cirujano con autismo y síndrome de erudito, se traslada de una vida tranquila en el campo para unirse a la prestigiosa unidad quirúrgica de un hospital. Solo en el mundo y sin poder conectarse personalmente con quienes lo rodean, Shaun utiliza sus extraordinarios dones médicos para salvar vidas y desafiar el escepticismo de sus colegas."
    },
    {
      "show_name": "The Good Doctor",
      "show_logo": "https://imagenes.gatotv.com/categorias/programas/miniatura/the_good_doctor.jpg",
      "start_time": "2026-02-01 05:00:00",
      "end_time": "2026-02-01 06:00:00",
      "episode_number": "S1 E16",
      "show_category": "Drama",
      "show_description": "Shaun Murphy (Freddie Highmore) es un joven cirujano con autismo y síndrome de erudito, se traslada de una vida tranquila en el campo para unirse a la prestigiosa unidad quirúrgica de un hospital. Solo en el mundo y sin poder conectarse personalmente con quienes lo rodean, Shaun utiliza sus extraordinarios dones médicos para salvar vidas y desafiar el escepticismo de sus colegas."
    },
    {
      "show_name": "Enloqueciendo Contigo",
      "show_logo": "",
      "start_time": "2026-02-01 06:00:00",
      "end_time": "2026-02-01 06:30:00",
      "episode_number": "S1 E9",
      "show_category": "",
      "show_description": ""
    },
    {
      "show_name": "Enloqueciendo Contigo",
      "show_logo": "",
      "start_time": "2026-02-01 06:30:00",
      "end_time": "2026-02-01 07:00:00",
      "episode_number": "S1 E10",
      "show_category": "",
      "show_description": ""
    },
    {
      "show_name": "Enloqueciendo Contigo",
      "show_logo": "",
      "start_time": "2026-02-01 07:00:00",
      "end_time": "2026-02-01 07:30:00",
      "episode_number": "S1 E11",
      "show_category": "",
      "show_description": ""
    },
    {
      "show_name": "Enloqueciendo Contigo",
      "show_logo": "",
      "start_time": "2026-02-01 07:30:00",
      "end_time": "2026-02-01 08:15:00",
      "episode_number": "S1 E12",
      "show_category": "",
      "show_description": ""
    },
    {
      "show_name": "Antes de partir",
      "show_logo": "",
      "start_time": "2026-02-01 08:15:00",
      "end_time": "2026-02-01 10:05:00",
      "episode_number": "",
      "show_category": "",
      "show_description": ""
    },
    {
      "show_name": "Juegos del Hambre Sinsajo, 2",
      "show_logo": "",
      "start_time": "2026-02-01 10:05:00",
      "end_time": "2026-02-01 12:35:00",
      "episode_number": "",
      "show_category": "",
      "show_description": ""
    },
    {
      "show_name": "La Mujer Rey",
      "show_logo": "https://imagenes.gatotv.com/categorias/peliculas/miniatura/la_mujer_rey.jpg",
      "start_time": "2026-02-01 12:35:00",
      "end_time": "2026-02-01 15:05:00",
      "episode_number": "",
      "show_category": "Acción",
      "show_description": "La Mujer Rey es la notable historia de Agojie, la unidad de guerras compuesta exclusivamente por mujeres que protegieron el reino africano de Dahomey en el siglo XIX con habilidades y una ferocidad como nunca ante se había visto en el mundo. Inspirada en hechos reales, La Mujer Rey sigue el viaje emocionalmente épico de la General Nanisca (Viola Davis) mientras entrena a la próxima generación de reclutas y las prepara para la batalla contra un enemigo decidido a destruir su forma de vida. Hay cosas por las que vale la pena luchar…."
    },
    {
      "show_name": "Venom: Carnage Liberado",
      "show_logo": "https://imagenes.gatotv.com/categorias/peliculas/miniatura/venom_carnage_liberado.jpg",
      "start_time": "2026-02-01 15:05:00",
      "end_time": "2026-02-01 16:45:00",
      "episode_number": "",
      "show_category": "Acción",
      "show_description": "Eddie Brock (Tom Hardy) debe adaptarse a su nueva vida con el simbionte alienígena Venom. Para recuperar su vida, Eddie se propone hacerle una entrevista al asesino en serie Cletus Kasady (Woody Harrelson) antes que reciba la inyección letal, sin saber que Kasady pronto se convertirá en el nuevo anfitrión del simbionte Carnage."
    },
    {
      "show_name": "The Fast and the Furious",
      "show_logo": "https://imagenes.gatotv.com/categorias/peliculas/miniatura/rapido_y_furioso.jpg",
      "start_time": "2026-02-01 16:45:00",
      "end_time": "2026-02-01 18:45:00",
      "episode_number": "",
      "show_category": "Acción",
      "show_description": "Tienen la adrenalina y las máquinas malas, pero, sobre todo, tienen una necesidad extrema de velocidad. En las calles cargadas de turbo de Los Ángeles, cada noche es una carrera de campeonato. Con la furia potenciada por el nitro, Dominic Toretto (Vin Diesel), gobierna el camino convirtiendo a todos sus rivales en polvo. Él y su rival, Johnny Tran (Rick Yune) son los más audaces, los más malos y los mejores. Pero ahora, hay nueva rabia en el camino. Saben que es duro, saben que es rápido, pero lo que no saben es que es un detective demoníaco de la velocidad (Paul Walker) con suficiente empuje y determinación para salir victorioso. Con una intensa acción a toda velocidad, increíbles acrobacias a alta velocidad y pedal a fondo hasta la máxima intensidad, este asalto rápido y furioso te pone en el asiento del conductor y te desafía a superar todos los límites."
    },
    {
      "show_name": "+ Rápido + Furioso",
      "show_logo": "",
      "start_time": "2026-02-01 18:45:00",
      "end_time": "2026-02-01 20:45:00",
      "episode_number": "",
      "show_category": "",
      "show_description": ""
    },
    {
      "show_name": "Bad Boys Para Siempre",
      "show_logo": "https://imagenes.gatotv.com/categorias/peliculas/miniatura/bad_boys_para_siempre.jpg",
      "start_time": "2026-02-01 20:45:00",
      "end_time": "2026-02-01 23:00:00",
      "episode_number": "",
      "show_category": "Acción",
      "show_description": "Los Bad Boys: Michael \"Mike\" Lowrey (Will Smith) y Marcus Burnett (Martin Lawrence) vuelven a estar juntos para un último viaje en el muy esperado Bad Boys Para Siempre."
    },
    {
      "show_name": "Enloqueciendo Contigo",
      "show_logo": "",
      "start_time": "2026-02-01 23:00:00",
      "end_time": "2026-02-01 23:30:00",
      "episode_number": "S2 E2",
      "show_category": "",
      "show_description": ""
    },
    {
      "show_name": "+ Rápido + Furioso",
      "show_logo": "",
      "start_time": "2026-02-01 23:30:00",
      "end_time": "2026-02-02 01:30:00",
      "episode_number": "",
      "show_category": "",
      "show_description": ""
    }
  ]
}