{
  "channel": "Cinema",
  "date": "10/03/2026",
  "schedule": [
    {
      "show_name": "Bataclan mexicano",
      "show_logo": "",
      "show_category": "",
      "start_time": "00:00",
      "end_time": "01:15",
      "episode_description": ""
    },
    {
      "show_name": "Échenme al gato",
      "show_logo": "",
      "show_category": "",
      "start_time": "01:15",
      "end_time": "03:00",
      "episode_description": ""
    },
    {
      "show_name": "Misericordia",
      "show_logo": "",
      "show_category": "",
      "start_time": "03:00",
      "end_time": "04:45",
      "episode_description": ""
    },
    {
      "show_name": "El lunar de la familia",
      "show_logo": "",
      "show_category": "",
      "start_time": "04:45",
      "end_time": "06:00",
      "episode_description": ""
    },
    {
      "show_name": "Música, espuelas y amor",
      "show_logo": "",
      "show_category": "",
      "start_time": "06:00",
      "end_time": "07:45",
      "episode_description": ""
    },
    {
      "show_name": "El Encuentro de un Hombre Solo",
      "show_logo": "",
      "show_category": "",
      "start_time": "07:45",
      "end_time": "09:30",
      "episode_description": ""
    },
    {
      "show_name": "Herencia Maldita",
      "show_logo": "",
      "show_category": "",
      "start_time": "09:30",
      "end_time": "11:15",
      "episode_description": ""
    },
    {
      "show_name": "Juego peligroso",
      "show_logo": "",
      "show_category": "",
      "start_time": "11:15",
      "end_time": "13:00",
      "episode_description": ""
    },
    {
      "show_name": "La mujer que engañamos",
      "show_logo": "",
      "show_category": "",
      "start_time": "13:00",
      "end_time": "14:45",
      "episode_description": ""
    },
    {
      "show_name": "Los tres valientes camaradas",
      "show_logo": "",
      "show_category": "",
      "start_time": "14:45",
      "end_time": "16:30",
      "episode_description": ""
    },
    {
      "show_name": "Mi madre es culpable",
      "show_logo": "",
      "show_category": "",
      "start_time": "16:30",
      "end_time": "18:15",
      "episode_description": ""
    },
    {
      "show_name": "Viva la parranda",
      "show_logo": "",
      "show_category": "",
      "start_time": "18:15",
      "end_time": "20:00",
      "episode_description": ""
    },
    {
      "show_name": "El joven del carrito",
      "show_logo": "",
      "show_category": "",
      "start_time": "20:00",
      "end_time": "21:45",
      "episode_description": ""
    },
    {
      "show_name": "Marcelo y María",
      "show_logo": "",
      "show_category": "",
      "start_time": "21:45",
      "end_time": "23:30",
      "episode_description": ""
    },
    {
      "show_name": "Música, espuelas y amor",
      "show_logo": "",
      "show_category": "",
      "start_time": "23:30",
      "end_time": "01:15",
      "episode_description": ""
    }
  ]
}