{
  "channel": "HBO Mundi",
  "date": "20/02/2026",
  "schedule": [
    {
      "show_name": "Waltz with bashir",
      "show_logo": "",
      "show_category": "",
      "start_time": "00:00",
      "end_time": "01:20",
      "episode_description": ""
    },
    {
      "show_name": "Río Helado",
      "show_logo": "",
      "show_category": "",
      "start_time": "01:20",
      "end_time": "03:00",
      "episode_description": ""
    },
    {
      "show_name": "The Beacon",
      "show_logo": "",
      "show_category": "",
      "start_time": "03:00",
      "end_time": "04:45",
      "episode_description": ""
    },
    {
      "show_name": "The Front Room",
      "show_logo": "",
      "show_category": "",
      "start_time": "04:45",
      "end_time": "06:25",
      "episode_description": ""
    },
    {
      "show_name": "¡Huye!",
      "show_logo": "https://programaciontv.com.mx/wp-content/uploads/downloaded-images/HBO-Mundi/today/huye.webp",
      "show_category": "Terror",
      "start_time": "06:25",
      "end_time": "08:15",
      "episode_description": "Cuando Chris (Daniel Kaluuya), un joven afroamericano, visita la familia de su novia de tez blanca, Rose Armitage (Allison Williams), se encuentra atrapado en la verdadera razón del porqué de su invitación. Al principio, Chris lee el comportamiento demasiado complaciente de la familia mientras intenta calmar sus nervios tratando de lidiar con la relación interracial con su hija, pero a medida que avanza el fin de semana, una serie de descubrimientos inquietantes lo llevan a una verdad que nunca podría haber imaginado."
    },
    {
      "show_name": "El sustituto",
      "show_logo": "",
      "show_category": "",
      "start_time": "08:15",
      "end_time": "10:45",
      "episode_description": ""
    },
    {
      "show_name": "Expiación, deseo y pecado",
      "show_logo": "",
      "show_category": "",
      "start_time": "10:45",
      "end_time": "12:55",
      "episode_description": ""
    },
    {
      "show_name": "The Settlers",
      "show_logo": "",
      "show_category": "",
      "start_time": "12:55",
      "end_time": "14:40",
      "episode_description": ""
    },
    {
      "show_name": "El Infiltrado del KKKlan",
      "show_logo": "https://programaciontv.com.mx/wp-content/uploads/downloaded-images/HBO-Mundi/today/el-infiltrado-del-kkklan.webp",
      "show_category": "Biografía",
      "start_time": "14:40",
      "end_time": "17:00",
      "episode_description": "La increíble y verdadera historia de un héroe americano. A principios de la década de 1970, y Ron Stallworth (John David Washington) es el primer detective afroamericano en servir al Departamento de Policía de Colorado Springs. Decidido a hacerse de un nombre, Stallworth se embarca valientemente en una misión peligrosa: Infiltrarse y exponer al Ku Klux Klan. El joven detective pronto recluta a un colega más experimentado, Flip Zimmerman (Adam Driver), en la investigación secreta de su vida. Juntos, se unen para derrotar al grupo extremista de odio mientras la organización busca desinfectar su retórica violenta para atraer la corriente popular."
    },
    {
      "show_name": "Monkey Man El despertar",
      "show_logo": "",
      "show_category": "",
      "start_time": "17:00",
      "end_time": "19:05",
      "episode_description": ""
    },
    {
      "show_name": "HBO Movies",
      "show_logo": "",
      "show_category": "",
      "start_time": "19:05",
      "end_time": "20:00",
      "episode_description": ""
    },
    {
      "show_name": "Nosotros",
      "show_logo": "",
      "show_category": "",
      "start_time": "20:00",
      "end_time": "22:00",
      "episode_description": ""
    },
    {
      "show_name": "HBO Movies",
      "show_logo": "",
      "show_category": "",
      "start_time": "22:00",
      "end_time": "22:55",
      "episode_description": ""
    },
    {
      "show_name": "¡Huye!",
      "show_logo": "https://programaciontv.com.mx/wp-content/uploads/downloaded-images/HBO-Mundi/today/huye.webp",
      "show_category": "Terror",
      "start_time": "22:55",
      "end_time": "00:45",
      "episode_description": "Cuando Chris (Daniel Kaluuya), un joven afroamericano, visita la familia de su novia de tez blanca, Rose Armitage (Allison Williams), se encuentra atrapado en la verdadera razón del porqué de su invitación. Al principio, Chris lee el comportamiento demasiado complaciente de la familia mientras intenta calmar sus nervios tratando de lidiar con la relación interracial con su hija, pero a medida que avanza el fin de semana, una serie de descubrimientos inquietantes lo llevan a una verdad que nunca podría haber imaginado."
    }
  ]
}