{
  "channel": "HBO Pop",
  "date": "10/03/2026",
  "schedule": [
    {
      "show_name": "After amor infinito",
      "show_logo": "",
      "show_category": "",
      "start_time": "00:00",
      "end_time": "00:20",
      "episode_description": ""
    },
    {
      "show_name": "H.Potter y la cámara secreta",
      "show_logo": "",
      "show_category": "",
      "start_time": "00:20",
      "end_time": "03:00",
      "episode_description": ""
    },
    {
      "show_name": "H.Potter y la cámara secreta",
      "show_logo": "",
      "show_category": "",
      "start_time": "03:00",
      "end_time": "05:43",
      "episode_description": ""
    },
    {
      "show_name": "El Increíble Burt Wonderstone",
      "show_logo": "",
      "show_category": "",
      "start_time": "05:43",
      "end_time": "07:25",
      "episode_description": ""
    },
    {
      "show_name": "Dale duro",
      "show_logo": "",
      "show_category": "",
      "start_time": "07:25",
      "end_time": "09:10",
      "episode_description": ""
    },
    {
      "show_name": "Ritmo perfecto",
      "show_logo": "",
      "show_category": "",
      "start_time": "09:10",
      "end_time": "11:05",
      "episode_description": ""
    },
    {
      "show_name": "La Boda de mi Ex",
      "show_logo": "https://programaciontv.com.mx/wp-content/uploads/downloaded-images/HBO-Pop/today/la-boda-de-mi-ex.webp",
      "show_category": "Drama",
      "start_time": "11:05",
      "end_time": "12:35",
      "episode_description": "Lindsay (Winona Ryder) y Frank (Keanu Reeves), socialmente torpes. Cuando se topan en su camino hacia una boda, pronto descubren tiene mucho en común: ambos odian a la novia, al novio, a la boda, a ellos mismos, y especialmente a los demás. A medida que los eventos del fin de semana los obligan a unirse – y su tristeza los aísla de los demás invitados – Frank y Lindsay descubren que, si luchas verbalmente con alguien lo suficiente, cualquier cosa puede suceder. Cuando el debate da paso al deseo, deben decidir cuál es más fuerte: Sus corazones o su sentido común."
    },
    {
      "show_name": "Quiero matar a mi jefe",
      "show_logo": "",
      "show_category": "",
      "start_time": "12:35",
      "end_time": "14:15",
      "episode_description": ""
    },
    {
      "show_name": "Quiero matar a mi jefe 2",
      "show_logo": "",
      "show_category": "",
      "start_time": "14:15",
      "end_time": "16:05",
      "episode_description": ""
    },
    {
      "show_name": "Los Huéspedes",
      "show_logo": "",
      "show_category": "",
      "start_time": "16:05",
      "end_time": "17:45",
      "episode_description": ""
    },
    {
      "show_name": "Dale duro",
      "show_logo": "",
      "show_category": "",
      "start_time": "17:45",
      "end_time": "19:30",
      "episode_description": ""
    },
    {
      "show_name": "DTF St. Louis",
      "show_logo": "",
      "show_category": "",
      "start_time": "19:30",
      "end_time": "20:30",
      "episode_description": ""
    },
    {
      "show_name": "HBO Movies",
      "show_logo": "",
      "show_category": "",
      "start_time": "20:30",
      "end_time": "21:00",
      "episode_description": ""
    },
    {
      "show_name": "No me las Toquen",
      "show_logo": "https://programaciontv.com.mx/wp-content/uploads/downloaded-images/HBO-Pop/today/no-me-las-toquen.webp",
      "show_category": "Comedia",
      "start_time": "21:00",
      "end_time": "22:43",
      "episode_description": "Cuando tres padres descubren el pacto de sus hijas para perder su virginidad en la fiesta de graduación se lanzan en una operación encubierta de una sola noche para evitar que las adolescentes cierren el trato."
    },
    {
      "show_name": "DTF St. Louis",
      "show_logo": "",
      "show_category": "",
      "start_time": "22:43",
      "end_time": "23:43",
      "episode_description": ""
    },
    {
      "show_name": "Click perdiendo el control",
      "show_logo": "",
      "show_category": "",
      "start_time": "23:43",
      "end_time": "01:32",
      "episode_description": ""
    }
  ]
}