{
  "channel": "14 de México",
  "date": "08/03/2026",
  "schedule": [
    {
      "show_name": "Encuentro inesperado",
      "show_logo": "",
      "show_category": "",
      "start_time": "00:00",
      "end_time": "01:05",
      "episode_description": ""
    },
    {
      "show_name": "Bajo el Volcán",
      "show_logo": "",
      "show_category": "",
      "start_time": "01:05",
      "end_time": "04:00",
      "episode_description": ""
    },
    {
      "show_name": "Honores Policiales",
      "show_logo": "",
      "show_category": "",
      "start_time": "04:00",
      "end_time": "05:35",
      "episode_description": ""
    },
    {
      "show_name": "Biografías de Películas con En",
      "show_logo": "",
      "show_category": "",
      "start_time": "05:35",
      "end_time": "06:05",
      "episode_description": ""
    },
    {
      "show_name": "Cartas para la libertad",
      "show_logo": "",
      "show_category": "",
      "start_time": "06:05",
      "end_time": "06:50",
      "episode_description": ""
    },
    {
      "show_name": "La calle, el aula y la pantall",
      "show_logo": "",
      "show_category": "",
      "start_time": "06:50",
      "end_time": "07:15",
      "episode_description": ""
    },
    {
      "show_name": "Conversando Cristina Pacheco",
      "show_logo": "",
      "show_category": "",
      "start_time": "07:15",
      "end_time": "08:15",
      "episode_description": ""
    },
    {
      "show_name": "Ama de Casa",
      "show_logo": "",
      "show_category": "",
      "start_time": "08:15",
      "end_time": "09:05",
      "episode_description": ""
    },
    {
      "show_name": "Noticiario France 24",
      "show_logo": "",
      "show_category": "",
      "start_time": "09:05",
      "end_time": "10:10",
      "episode_description": ""
    },
    {
      "show_name": "Reportaje 14",
      "show_logo": "",
      "show_category": "",
      "start_time": "10:10",
      "end_time": "10:40",
      "episode_description": ""
    },
    {
      "show_name": "Reportaje 14",
      "show_logo": "",
      "show_category": "",
      "start_time": "10:40",
      "end_time": "11:10",
      "episode_description": ""
    },
    {
      "show_name": "Trotacalles",
      "show_logo": "",
      "show_category": "",
      "start_time": "11:10",
      "end_time": "12:55",
      "episode_description": ""
    },
    {
      "show_name": "La Femenil, la lucha no acaba",
      "show_logo": "",
      "show_category": "",
      "start_time": "12:55",
      "end_time": "14:30",
      "episode_description": ""
    },
    {
      "show_name": "La Lucha se Hace",
      "show_logo": "",
      "show_category": "",
      "start_time": "14:30",
      "end_time": "15:00",
      "episode_description": ""
    },
    {
      "show_name": "Salud y Deporte",
      "show_logo": "",
      "show_category": "",
      "start_time": "15:00",
      "end_time": "16:00",
      "episode_description": ""
    },
    {
      "show_name": "Grandes Figuras del Arte",
      "show_logo": "",
      "show_category": "",
      "start_time": "16:00",
      "end_time": "17:00",
      "episode_description": ""
    },
    {
      "show_name": "Rimas Moradas",
      "show_logo": "",
      "show_category": "",
      "start_time": "17:00",
      "end_time": "18:00",
      "episode_description": ""
    },
    {
      "show_name": "Mujer en Cypher en el Zócalo",
      "show_logo": "",
      "show_category": "",
      "start_time": "18:00",
      "end_time": "19:00",
      "episode_description": ""
    },
    {
      "show_name": "8M Nuestras Causas",
      "show_logo": "",
      "show_category": "",
      "start_time": "19:00",
      "end_time": "20:00",
      "episode_description": ""
    },
    {
      "show_name": "Versiones Públicas",
      "show_logo": "",
      "show_category": "",
      "start_time": "20:00",
      "end_time": "21:00",
      "episode_description": ""
    },
    {
      "show_name": "Ventana al Mundo",
      "show_logo": "",
      "show_category": "",
      "start_time": "21:00",
      "end_time": "21:30",
      "episode_description": ""
    },
    {
      "show_name": "Los Secretos de la Corrupción",
      "show_logo": "",
      "show_category": "",
      "start_time": "21:30",
      "end_time": "22:00",
      "episode_description": ""
    },
    {
      "show_name": "Debate Público",
      "show_logo": "",
      "show_category": "",
      "start_time": "22:00",
      "end_time": "23:00",
      "episode_description": ""
    },
    {
      "show_name": "La Cucaracha",
      "show_logo": "",
      "show_category": "",
      "start_time": "23:00",
      "end_time": "00:35",
      "episode_description": ""
    }
  ]
}