{
  "channel": "Bandamax",
  "date": "08/03/2026",
  "schedule": [
    {
      "show_name": "El show del hombre",
      "show_logo": "",
      "show_category": "",
      "start_time": "00:00",
      "end_time": "00:25",
      "episode_description": ""
    },
    {
      "show_name": "Bandamáximo Dolor",
      "show_logo": "",
      "show_category": "",
      "start_time": "00:25",
      "end_time": "01:25",
      "episode_description": ""
    },
    {
      "show_name": "Las imperdibles BDX",
      "show_logo": "",
      "show_category": "",
      "start_time": "01:25",
      "end_time": "03:45",
      "episode_description": ""
    },
    {
      "show_name": "Bandamáximo Dolor",
      "show_logo": "",
      "show_category": "",
      "start_time": "03:45",
      "end_time": "04:40",
      "episode_description": ""
    },
    {
      "show_name": "Colaboreme Compa",
      "show_logo": "",
      "show_category": "",
      "start_time": "04:40",
      "end_time": "05:05",
      "episode_description": ""
    },
    {
      "show_name": "Mi versión en Bandamax",
      "show_logo": "",
      "show_category": "",
      "start_time": "05:05",
      "end_time": "05:35",
      "episode_description": ""
    },
    {
      "show_name": "Viejitas pero Sabrosas",
      "show_logo": "",
      "show_category": "",
      "start_time": "05:35",
      "end_time": "06:05",
      "episode_description": ""
    },
    {
      "show_name": "Viejitas pero Sabrosas",
      "show_logo": "",
      "show_category": "",
      "start_time": "06:05",
      "end_time": "06:30",
      "episode_description": ""
    },
    {
      "show_name": "Los Consagrados de Bandamax",
      "show_logo": "",
      "show_category": "",
      "start_time": "06:30",
      "end_time": "07:00",
      "episode_description": ""
    },
    {
      "show_name": "Las consagradas de Bandamax",
      "show_logo": "",
      "show_category": "",
      "start_time": "07:00",
      "end_time": "07:30",
      "episode_description": ""
    },
    {
      "show_name": "Las mas sonadas",
      "show_logo": "",
      "show_category": "",
      "start_time": "07:30",
      "end_time": "09:45",
      "episode_description": ""
    },
    {
      "show_name": "2X1 Bandamax",
      "show_logo": "",
      "show_category": "",
      "start_time": "09:45",
      "end_time": "10:15",
      "episode_description": ""
    },
    {
      "show_name": "Los Consagrados de Bandamax",
      "show_logo": "",
      "show_category": "",
      "start_time": "10:15",
      "end_time": "10:40",
      "episode_description": ""
    },
    {
      "show_name": "Las consagradas de Bandamax",
      "show_logo": "",
      "show_category": "",
      "start_time": "10:40",
      "end_time": "11:10",
      "episode_description": ""
    },
    {
      "show_name": "El show del hombre",
      "show_logo": "",
      "show_category": "",
      "start_time": "11:10",
      "end_time": "12:05",
      "episode_description": ""
    },
    {
      "show_name": "Banda y Max",
      "show_logo": "",
      "show_category": "",
      "start_time": "12:05",
      "end_time": "13:30",
      "episode_description": ""
    },
    {
      "show_name": "Viejitas pero Sabrosas",
      "show_logo": "",
      "show_category": "",
      "start_time": "13:30",
      "end_time": "13:55",
      "episode_description": ""
    },
    {
      "show_name": "Las Divas de Bandamax",
      "show_logo": "",
      "show_category": "",
      "start_time": "13:55",
      "end_time": "14:50",
      "episode_description": ""
    },
    {
      "show_name": "La parrilla del fuego",
      "show_logo": "",
      "show_category": "",
      "start_time": "14:50",
      "end_time": "15:45",
      "episode_description": ""
    },
    {
      "show_name": "Banda y Max",
      "show_logo": "",
      "show_category": "",
      "start_time": "15:45",
      "end_time": "16:40",
      "episode_description": ""
    },
    {
      "show_name": "2X1 Bandamax",
      "show_logo": "",
      "show_category": "",
      "start_time": "16:40",
      "end_time": "17:05",
      "episode_description": ""
    },
    {
      "show_name": "Las mas sonadas",
      "show_logo": "",
      "show_category": "",
      "start_time": "17:05",
      "end_time": "18:00",
      "episode_description": ""
    },
    {
      "show_name": "Banda y Max",
      "show_logo": "",
      "show_category": "",
      "start_time": "18:00",
      "end_time": "19:25",
      "episode_description": ""
    },
    {
      "show_name": "Regional Clasificado",
      "show_logo": "",
      "show_category": "",
      "start_time": "19:25",
      "end_time": "19:50",
      "episode_description": ""
    },
    {
      "show_name": "Las imperdibles BDX",
      "show_logo": "",
      "show_category": "",
      "start_time": "19:50",
      "end_time": "21:15",
      "episode_description": ""
    },
    {
      "show_name": "Los reyes del regional",
      "show_logo": "",
      "show_category": "",
      "start_time": "21:15",
      "end_time": "22:10",
      "episode_description": ""
    },
    {
      "show_name": "Los Consagrados de Bandamax",
      "show_logo": "",
      "show_category": "",
      "start_time": "22:10",
      "end_time": "22:40",
      "episode_description": ""
    },
    {
      "show_name": "Los patrones de Bandamax",
      "show_logo": "",
      "show_category": "",
      "start_time": "22:40",
      "end_time": "23:35",
      "episode_description": ""
    },
    {
      "show_name": "La cantina del tunco",
      "show_logo": "",
      "show_category": "",
      "start_time": "23:35",
      "end_time": "00:30",
      "episode_description": ""
    }
  ]
}