{
  "channel": "Discovery Home & Health (México)",
  "date": "04/02/2026",
  "schedule": [
    {
      "show_name": "Mi vida con Tourette",
      "show_logo": "",
      "show_category": "",
      "start_time": "00:00",
      "end_time": "00:11",
      "episode_description": ""
    },
    {
      "show_name": "Mi vida con Tourette",
      "show_logo": "",
      "show_category": "",
      "start_time": "00:11",
      "end_time": "01:00",
      "episode_description": ""
    },
    {
      "show_name": "Tacaños extremos",
      "show_logo": "",
      "show_category": "",
      "start_time": "01:00",
      "end_time": "01:25",
      "episode_description": ""
    },
    {
      "show_name": "Tacaños extremos",
      "show_logo": "",
      "show_category": "",
      "start_time": "01:25",
      "end_time": "01:50",
      "episode_description": ""
    },
    {
      "show_name": "El Gran Pastelero - Bake Off",
      "show_logo": "",
      "show_category": "",
      "start_time": "01:50",
      "end_time": "02:45",
      "episode_description": ""
    },
    {
      "show_name": "Divina Comida México",
      "show_logo": "",
      "show_category": "",
      "start_time": "02:45",
      "end_time": "03:34",
      "episode_description": ""
    },
    {
      "show_name": "Pesadilla en la cocina",
      "show_logo": "",
      "show_category": "",
      "start_time": "03:34",
      "end_time": "04:19",
      "episode_description": ""
    },
    {
      "show_name": "Sobre esta piel",
      "show_logo": "",
      "show_category": "",
      "start_time": "04:19",
      "end_time": "04:45",
      "episode_description": ""
    },
    {
      "show_name": "Sobre esta piel",
      "show_logo": "",
      "show_category": "",
      "start_time": "04:45",
      "end_time": "05:12",
      "episode_description": ""
    },
    {
      "show_name": "Mi vida con Tourette",
      "show_logo": "",
      "show_category": "",
      "start_time": "05:12",
      "end_time": "06:00",
      "episode_description": ""
    },
    {
      "show_name": "Rescatando propiedades Atlant",
      "show_logo": "",
      "show_category": "",
      "start_time": "06:00",
      "end_time": "06:26",
      "episode_description": ""
    },
    {
      "show_name": "Renovando mi ciudad",
      "show_logo": "",
      "show_category": "",
      "start_time": "06:26",
      "end_time": "07:15",
      "episode_description": ""
    },
    {
      "show_name": "¡Ayuda! Arruiné mi casa",
      "show_logo": "",
      "show_category": "",
      "start_time": "07:15",
      "end_time": "08:04",
      "episode_description": ""
    },
    {
      "show_name": "Las renovadoras",
      "show_logo": "",
      "show_category": "",
      "start_time": "08:04",
      "end_time": "08:54",
      "episode_description": ""
    },
    {
      "show_name": "Hermanos a la obra",
      "show_logo": "",
      "show_category": "",
      "start_time": "08:54",
      "end_time": "09:44",
      "episode_description": ""
    },
    {
      "show_name": "Rescata mi Restaurante",
      "show_logo": "",
      "show_category": "",
      "start_time": "09:44",
      "end_time": "10:33",
      "episode_description": ""
    },
    {
      "show_name": "Remodelaciones con celebridad",
      "show_logo": "",
      "show_category": "",
      "start_time": "10:33",
      "end_time": "11:24",
      "episode_description": ""
    },
    {
      "show_name": "La gran recompensa",
      "show_logo": "",
      "show_category": "",
      "start_time": "11:24",
      "end_time": "12:14",
      "episode_description": ""
    },
    {
      "show_name": "Transformando casas con los E",
      "show_logo": "",
      "show_category": "",
      "start_time": "12:14",
      "end_time": "13:05",
      "episode_description": ""
    },
    {
      "show_name": "Hermanos a la obra",
      "show_logo": "",
      "show_category": "",
      "start_time": "13:05",
      "end_time": "13:55",
      "episode_description": ""
    },
    {
      "show_name": "Historias de peso clínica de",
      "show_logo": "",
      "show_category": "",
      "start_time": "13:55",
      "end_time": "14:45",
      "episode_description": ""
    },
    {
      "show_name": "Clínica de la piel",
      "show_logo": "",
      "show_category": "",
      "start_time": "14:45",
      "end_time": "15:36",
      "episode_description": ""
    },
    {
      "show_name": "Batalla de hermanos",
      "show_logo": "",
      "show_category": "",
      "start_time": "15:36",
      "end_time": "16:26",
      "episode_description": ""
    },
    {
      "show_name": "Batalla de hermanos",
      "show_logo": "",
      "show_category": "",
      "start_time": "16:26",
      "end_time": "17:17",
      "episode_description": ""
    },
    {
      "show_name": "Sala de emergencias",
      "show_logo": "",
      "show_category": "",
      "start_time": "17:17",
      "end_time": "18:08",
      "episode_description": ""
    },
    {
      "show_name": "Aeropuerto de Sao Paulo",
      "show_logo": "",
      "show_category": "",
      "start_time": "18:08",
      "end_time": "18:33",
      "episode_description": ""
    },
    {
      "show_name": "Aeropuerto de Sao Paulo",
      "show_logo": "",
      "show_category": "",
      "start_time": "18:33",
      "end_time": "18:59",
      "episode_description": ""
    },
    {
      "show_name": "Remodelaciones con celebridad",
      "show_logo": "",
      "show_category": "",
      "start_time": "18:59",
      "end_time": "19:49",
      "episode_description": ""
    },
    {
      "show_name": "Transformando casas con los E",
      "show_logo": "",
      "show_category": "",
      "start_time": "19:49",
      "end_time": "20:40",
      "episode_description": ""
    },
    {
      "show_name": "La gran recompensa",
      "show_logo": "",
      "show_category": "",
      "start_time": "20:40",
      "end_time": "21:30",
      "episode_description": ""
    },
    {
      "show_name": "Gordon Ramsay servicio secret",
      "show_logo": "",
      "show_category": "",
      "start_time": "21:30",
      "end_time": "22:21",
      "episode_description": ""
    },
    {
      "show_name": "Pesadilla en la cocina",
      "show_logo": "",
      "show_category": "",
      "start_time": "22:21",
      "end_time": "23:12",
      "episode_description": ""
    },
    {
      "show_name": "Rescata mi Restaurante",
      "show_logo": "",
      "show_category": "",
      "start_time": "23:12",
      "end_time": "00:02",
      "episode_description": ""
    }
  ]
}